ml_approach_suggestion_agent/__init__.py
ml_approach_suggestion_agent/agent.py
ml_approach_suggestion_agent/config.py
ml_approach_suggestion_agent/constants.py
ml_approach_suggestion_agent/models.py
ml_approach_suggestion_agent-0.1.8.dist-info/METADATA
ml_approach_suggestion_agent-0.1.8.dist-info/WHEEL
ml_approach_suggestion_agent-0.1.8.dist-info/top_level.txt
ml_approach_suggestion_agent-0.1.8.dist-info/RECORD
