Metadata-Version: 2.4
Name: ml_approach_suggestion_agent
Version: 0.1.8
Summary: Add your description here
License-Expression: MIT
Classifier: Programming Language :: Python :: 3
Classifier: Programming Language :: Python :: 3.10
Classifier: Programming Language :: Python :: 3.11
Classifier: Programming Language :: Python :: 3.12
Classifier: Programming Language :: Python :: 3.13
Classifier: Operating System :: OS Independent
Requires-Python: >=3.11
Requires-Dist: pydantic-settings
Requires-Dist: sfn-blueprint>=0.6.16
Provides-Extra: dev
Requires-Dist: pytest; extra == "dev"
Requires-Dist: pytest-mock; extra == "dev"
